LICENSE
MANIFEST.in
README.md
VERSION
mbtt
minibus.py
requirements.txt
setup.py
examples/basic_publisher.py
examples/basic_service_client.py
examples/basic_service_server.py
examples/basic_subscriber.py
examples/encrypted_publisher.py
examples/encrypted_service_client.py
examples/encrypted_service_server.py
examples/encrypted_subscriber.py
examples/lagerlogger.py
examples/lagerlogger.pyc
examples/minibus.py
examples/minibus.pyc
examples/twisted_basic_publisher.py
examples/twisted_basic_service_client.py
examples/twisted_basic_service_client2.py
examples/twisted_basic_service_server.py
examples/twisted_basic_subscriber.py
examples/twisted_encrypted_publisher.py
examples/twisted_encrypted_service_client.py
examples/twisted_encrypted_service_server.py
examples/twisted_encrypted_subscriber.py
examples/typed_publisher.py
examples/typed_subscriber.py
minibus.egg-info/PKG-INFO
minibus.egg-info/SOURCES.txt
minibus.egg-info/dependency_links.txt
minibus.egg-info/requires.txt
minibus.egg-info/top_level.txt