Metadata-Version: 1.1
Name: minibus
Version: 0.3.0
Summary: MiniBus IPC Library
Home-page: https://github.com/mrdanbrooks/minibus
Author: Dan Brooks
Author-email: UNKNOWN
License: Apache v2.0
Keywords: minibus,publish/subscribe,ipc,development
Platform: UNKNOWN
Classifier: Development Status :: 3 - Alpha
Classifier: Intended Audience :: Developers
Classifier: Topic :: Software Development :: Libraries
Classifier: License :: OSI Approved :: Apache Software License
Classifier: Programming Language :: Python :: 2.7
